arkimedes/__init__.py
arkimedes/__main__.py
arkimedes/config.py
arkimedes/db.py
arkimedes/ead.py
arkimedes/ezid.py
arkimedes/pdf.py
arkimedes/qa.py
arkimedes-2022.7.12.dist-info/METADATA
arkimedes-2022.7.12.dist-info/WHEEL
arkimedes-2022.7.12.dist-info/entry_points.txt
arkimedes-2022.7.12.dist-info/top_level.txt
arkimedes-2022.7.12.dist-info/RECORD
